cryptochaos/__init__.py
cryptochaos/logistic.py
cryptochaos-1.0.0.dist-info/LICENSE.txt
cryptochaos-1.0.0.dist-info/METADATA
cryptochaos-1.0.0.dist-info/WHEEL
cryptochaos-1.0.0.dist-info/top_level.txt
cryptochaos-1.0.0.dist-info/RECORD
